pr_publisher/__init__.py
pr_publisher/cli.py
pr_publisher/const.py
pr_publisher/entry.py
pr_publisher/main.py
pr_publisher/publishers/__init__.py
pr_publisher/publishers/base.py
pr_publisher/publishers/slack.py
pr_publisher/publishers/table.py
tests/__init__.py
pr_publisher-0.0.2.dist-info/LICENSE
pr_publisher-0.0.2.dist-info/METADATA
pr_publisher-0.0.2.dist-info/WHEEL
pr_publisher-0.0.2.dist-info/entry_points.txt
pr_publisher-0.0.2.dist-info/top_level.txt
pr_publisher-0.0.2.dist-info/RECORD
