Metadata-Version: 2.1
Name: pr-publisher
Version: 0.0.2
Summary: publish a list of open pull requests
Home-page: https://github.com/pglass/pr-publisher
Author: Paul Glass
Author-email: pnglass@gmail.com
License: MIT
Keywords: github slack pull request list publish remind
Platform: UNKNOWN
Classifier: Development Status :: 4 - Beta
Classifier: Environment :: Console
Classifier: Intended Audience :: Developers
Classifier: License :: OSI Approved :: MIT License
Classifier: Operating System :: OS Independent
Classifier: Programming Language :: Python :: 2.7
Classifier: Programming Language :: Python :: 3.6
Classifier: Programming Language :: Python :: 3.7
Requires-Dist: PTable (==0.9.2)
Requires-Dist: ConfigArgParse (==0.14.0)
Requires-Dist: github3.py (==1.3.0)
Requires-Dist: requests (==2.21.0)
